okxos/__init__.py
okxos/client.py
okxos/defi.py
okxos/dex.py
okxos/marketplace.py
okxos/wallet.py
okxos-0.1.3.dist-info/METADATA
okxos-0.1.3.dist-info/WHEEL
okxos-0.1.3.dist-info/top_level.txt
okxos-0.1.3.dist-info/RECORD
