Metadata-Version: 2.1
Name: okxos
Version: 0.1.3
Summary: A Python client for OKX OS APIs
Home-page: https://github.com/yourusername/okxos
Author: bobo
Author-email: your_email@example.com
Classifier: Programming Language :: Python :: 3
Classifier: License :: OSI Approved :: MIT License
Classifier: Operating System :: OS Independent
Requires-Python: >=3.8
Requires-Dist: httpx>=0.24.1
